{"id": "neural_semigroups.utils", "path": "/home/inpefess/projects/neural-semigroups/neural_semigroups/utils.py", "mtime": 1584819542, "size": 8433, "hash": "f69eb90a8a5f04d3c2a72de1f723330e0a733fab16d38d195b3bb78e29a4d905", "data_mtime": 1584291417, "dependencies": ["itertools", "typing", "numpy", "neural_semigroups.magma", "builtins", "abc"], "suppressed": [], "options": {"ignore_missing_imports": false, "warn_unreachable": false, "disallow_untyped_defs": false, "warn_unused_ignores": false, "always_true": [], "disallow_incomplete_defs": false, "disallow_any_expr": false, "disallow_any_generics": false, "disallow_any_unimported": false, "allow_untyped_globals": false, "strict_equality": false, "bazel": false, "disallow_any_explicit": false, "local_partial_types": false, "disallow_untyped_calls": false, "implicit_reexport": true, "mypyc": false, "follow_imports_for_stubs": false, "no_implicit_optional": false, "follow_imports": "normal", "strict_optional": true, "platform": "linux", "always_false": [], "disallow_subclassing_any": false, "disallow_untyped_decorators": false, "disallow_any_decorated": false, "show_none_errors": true, "strict_optional_whitelist": null, "check_untyped_defs": false, "allow_redefinition": false, "warn_return_any": false, "ignore_errors": false, "plugins": [], "warn_no_return": true}, "dep_prios": [5, 5, 10, 5, 5, 30], "dep_lines": [16, 17, 19, 21, 1, 1], "interface_hash": "16fb71e3ce0126dabf76ac032ff93c262944a208be2ab0e376eec0dd9690eb99", "version_id": "0.770", "ignore_all": false, "plugin_data": null}